[{"ธนาคาร":"ธนาคารกสิกรไทย","('ราคาที่ธนาคารรับซื้อ', 'ธนบัตร')":"34.88074","('ราคาที่ธนาคารรับซื้อ', 'ตั๋วเงิน')":"35.26255","('ราคาที่ธนาคารรับซื้อ', 'เช็คเดินทาง')":"35.26255","('ราคาที่ธนาคารรับซื้อ', 'ตั๋วแลกเงิน&ดราฟ')":"-","('ราคาที่ธนาคารรับซื้อ', 'โอนเงินทางโทรเลข\/โอนเงิน')":"35.37041","('ราคาที่ธนาคารขาย', 'ธนบัตร')":"36.12509","('ราคาที่ธนาคารขาย', 'เช็คเดินทาง')":"36.04833","('ราคาที่ธนาคารขาย', 'ตั๋วแลกเงิน&ดราฟ')":"36.04833","('ราคาที่ธนาคารขาย', 'โอนเงินทางโทรเลข\/โอนเงิน')":"36.04833"},{"ธนาคาร":"ธนาคารไทยพาณิชย์","('ราคาที่ธนาคารรับซื้อ', 'ธนบัตร')":"34.80625","('ราคาที่ธนาคารรับซื้อ', 'ตั๋วเงิน')":"35.2675","('ราคาที่ธนาคารรับซื้อ', 'เช็คเดินทาง')":"35.1775","('ราคาที่ธนาคารรับซื้อ', 'ตั๋วแลกเงิน&ดราฟ')":"-","('ราคาที่ธนาคารรับซื้อ', 'โอนเงินทางโทรเลข\/โอนเงิน')":"35.3675","('ราคาที่ธนาคารขาย', 'ธนบัตร')":"36.1575","('ราคาที่ธนาคารขาย', 'เช็คเดินทาง')":"36.0825","('ราคาที่ธนาคารขาย', 'ตั๋วแลกเงิน&ดราฟ')":"36.0825","('ราคาที่ธนาคารขาย', 'โอนเงินทางโทรเลข\/โอนเงิน')":"-"},{"ธนาคาร":"ธนาคารกรุงเทพ","('ราคาที่ธนาคารรับซื้อ', 'ธนบัตร')":"34.76","('ราคาที่ธนาคารรับซื้อ', 'ตั๋วเงิน')":"-","('ราคาที่ธนาคารรับซื้อ', 'เช็คเดินทาง')":"-","('ราคาที่ธนาคารรับซื้อ', 'ตั๋วแลกเงิน&ดราฟ')":"35.25250","('ราคาที่ธนาคารรับซื้อ', 'โอนเงินทางโทรเลข\/โอนเงิน')":"35.36250","('ราคาที่ธนาคารขาย', 'ธนบัตร')":"35.97","('ราคาที่ธนาคารขาย', 'เช็คเดินทาง')":"-","('ราคาที่ธนาคารขาย', 'ตั๋วแลกเงิน&ดราฟ')":"36.06750","('ราคาที่ธนาคารขาย', 'โอนเงินทางโทรเลข\/โอนเงิน')":"36.06750"},{"ธนาคาร":"ธนาคารกรุงไทย","('ราคาที่ธนาคารรับซื้อ', 'ธนบัตร')":"35.06","('ราคาที่ธนาคารรับซื้อ', 'ตั๋วเงิน')":"35.23","('ราคาที่ธนาคารรับซื้อ', 'เช็คเดินทาง')":"-","('ราคาที่ธนาคารรับซื้อ', 'ตั๋วแลกเงิน&ดราฟ')":"-","('ราคาที่ธนาคารรับซื้อ', 'โอนเงินทางโทรเลข\/โอนเงิน')":"35.33","('ราคาที่ธนาคารขาย', 'ธนบัตร')":"36.05","('ราคาที่ธนาคารขาย', 'เช็คเดินทาง')":"36.05","('ราคาที่ธนาคารขาย', 'ตั๋วแลกเงิน&ดราฟ')":"-","('ราคาที่ธนาคารขาย', 'โอนเงินทางโทรเลข\/โอนเงิน')":"-"},{"ธนาคาร":"ธนาคารกรุงศรีอยุธยา","('ราคาที่ธนาคารรับซื้อ', 'ธนบัตร')":"35.08000","('ราคาที่ธนาคารรับซื้อ', 'ตั๋วเงิน')":"35.13061","('ราคาที่ธนาคารรับซื้อ', 'เช็คเดินทาง')":"-","('ราคาที่ธนาคารรับซื้อ', 'ตั๋วแลกเงิน&ดราฟ')":"-","('ราคาที่ธนาคารรับซื้อ', 'โอนเงินทางโทรเลข\/โอนเงิน')":"35.25061","('ราคาที่ธนาคารขาย', 'ธนบัตร')":"36.05000","('ราคาที่ธนาคารขาย', 'เช็คเดินทาง')":"36.03405","('ราคาที่ธนาคารขาย', 'ตั๋วแลกเงิน&ดราฟ')":"36.03405","('ราคาที่ธนาคารขาย', 'โอนเงินทางโทรเลข\/โอนเงิน')":"36.03405"}]