[{"ธนาคาร":"ธนาคารกสิกรไทย","('ราคาที่ธนาคารรับซื้อ', 'ธนบัตร')":"4.8625","('ราคาที่ธนาคารรับซื้อ', 'ตั๋วเงิน')":"5.11054","('ราคาที่ธนาคารรับซื้อ', 'เช็คเดินทาง')":"-","('ราคาที่ธนาคารรับซื้อ', 'ตั๋วแลกเงิน&ดราฟ')":"-","('ราคาที่ธนาคารรับซื้อ', 'โอนเงินทางโทรเลข\/โอนเงิน')":"5.1593","('ราคาที่ธนาคารขาย', 'ธนบัตร')":"5.36078","('ราคาที่ธนาคารขาย', 'เช็คเดินทาง')":"5.29978","('ราคาที่ธนาคารขาย', 'ตั๋วแลกเงิน&ดราฟ')":"5.29978","('ราคาที่ธนาคารขาย', 'โอนเงินทางโทรเลข\/โอนเงิน')":"5.29978"},{"ธนาคาร":"ธนาคารไทยพาณิชย์","('ราคาที่ธนาคารรับซื้อ', 'ธนบัตร')":"4.82","('ราคาที่ธนาคารรับซื้อ', 'ตั๋วเงิน')":"5.0975","('ราคาที่ธนาคารรับซื้อ', 'เช็คเดินทาง')":"5.0975","('ราคาที่ธนาคารรับซื้อ', 'ตั๋วแลกเงิน&ดราฟ')":"-","('ราคาที่ธนาคารรับซื้อ', 'โอนเงินทางโทรเลข\/โอนเงิน')":"5.1425","('ราคาที่ธนาคารขาย', 'ธนบัตร')":"5.38925","('ราคาที่ธนาคารขาย', 'เช็คเดินทาง')":"5.335","('ราคาที่ธนาคารขาย', 'ตั๋วแลกเงิน&ดราฟ')":"5.335","('ราคาที่ธนาคารขาย', 'โอนเงินทางโทรเลข\/โอนเงิน')":"-"},{"ธนาคาร":"ธนาคารกรุงเทพ","('ราคาที่ธนาคารรับซื้อ', 'ธนบัตร')":"4.91","('ราคาที่ธนาคารรับซื้อ', 'ตั๋วเงิน')":"-","('ราคาที่ธนาคารรับซื้อ', 'เช็คเดินทาง')":"-","('ราคาที่ธนาคารรับซื้อ', 'ตั๋วแลกเงิน&ดราฟ')":"5.10250","('ราคาที่ธนาคารรับซื้อ', 'โอนเงินทางโทรเลข\/โอนเงิน')":"5.14500","('ราคาที่ธนาคารขาย', 'ธนบัตร')":"5.31","('ราคาที่ธนาคารขาย', 'เช็คเดินทาง')":"-","('ราคาที่ธนาคารขาย', 'ตั๋วแลกเงิน&ดราฟ')":"5.31500","('ราคาที่ธนาคารขาย', 'โอนเงินทางโทรเลข\/โอนเงิน')":"5.31500"},{"ธนาคาร":"ธนาคารกรุงไทย","('ราคาที่ธนาคารรับซื้อ', 'ธนบัตร')":"4.96","('ราคาที่ธนาคารรับซื้อ', 'ตั๋วเงิน')":"5.1119","('ราคาที่ธนาคารรับซื้อ', 'เช็คเดินทาง')":"-","('ราคาที่ธนาคารรับซื้อ', 'ตั๋วแลกเงิน&ดราฟ')":"-","('ราคาที่ธนาคารรับซื้อ', 'โอนเงินทางโทรเลข\/โอนเงิน')":"5.1467","('ราคาที่ธนาคารขาย', 'ธนบัตร')":"5.40","('ราคาที่ธนาคารขาย', 'เช็คเดินทาง')":"5.3142","('ราคาที่ธนาคารขาย', 'ตั๋วแลกเงิน&ดราฟ')":"-","('ราคาที่ธนาคารขาย', 'โอนเงินทางโทรเลข\/โอนเงิน')":"-"},{"ธนาคาร":"ธนาคารกรุงศรีอยุธยา","('ราคาที่ธนาคารรับซื้อ', 'ธนบัตร')":"4.88000","('ราคาที่ธนาคารรับซื้อ', 'ตั๋วเงิน')":"5.10821","('ราคาที่ธนาคารรับซื้อ', 'เช็คเดินทาง')":"-","('ราคาที่ธนาคารรับซื้อ', 'ตั๋วแลกเงิน&ดราฟ')":"-","('ราคาที่ธนาคารรับซื้อ', 'โอนเงินทางโทรเลข\/โอนเงิน')":"5.12821","('ราคาที่ธนาคารขาย', 'ธนบัตร')":"5.39000","('ราคาที่ธนาคารขาย', 'เช็คเดินทาง')":"5.32821","('ราคาที่ธนาคารขาย', 'ตั๋วแลกเงิน&ดราฟ')":"5.32821","('ราคาที่ธนาคารขาย', 'โอนเงินทางโทรเลข\/โอนเงิน')":"5.32821"}]